eeconvert/__init__.py
eeconvert-0.1.22.dist-info/DESCRIPTION.rst
eeconvert-0.1.22.dist-info/METADATA
eeconvert-0.1.22.dist-info/RECORD
eeconvert-0.1.22.dist-info/WHEEL
eeconvert-0.1.22.dist-info/metadata.json
eeconvert-0.1.22.dist-info/top_level.txt
