Metadata-Version: 2.0
Name: eeconvert
Version: 0.1.22
Summary: UNKNOWN
Home-page: http://github.com/rutgerhofste/eeconvert
Author: Rutger Hofste
Author-email: rutgerhofste@gmail.com
License: MIT
Platform: UNKNOWN
Requires-Dist: boto3
Requires-Dist: botocore
Requires-Dist: branca
Requires-Dist: earthengine-api
Requires-Dist: folium
Requires-Dist: geojson
Requires-Dist: geopandas
Requires-Dist: pandas
Requires-Dist: shapely
Requires-Dist: sqlalchemy
